jelastic/__init__.py
jelastic/api/__init__.py
jelastic/api/abstract.py
jelastic/api/exceptions.py
jelastic/api/administration/__init__.py
jelastic/api/automation/__init__.py
jelastic/api/billing/__init__.py
jelastic/api/data/__init__.py
jelastic/api/development/__init__.py
jelastic/api/environment/__init__.py
jelastic/api/iaas/__init__.py
jelastic/api/io/__init__.py
jelastic/api/management/__init__.py
jelastic/api/marketplace/__init__.py
jelastic/api/message/__init__.py
jelastic/api/migration/__init__.py
jelastic/api/platform/__init__.py
jelastic/api/pool/__init__.py
jelastic/api/pricing/__init__.py
jelastic/api/s3/__init__.py
jelastic/api/security/__init__.py
jelastic/api/statistic/__init__.py
jelastic/api/system/__init__.py
jelastic/api/thirdparty/__init__.py
jelastic/api/users/__init__.py
jelastic/api/utils/__init__.py
py_jelastic-0.1.6.dist-info/LICENSE
py_jelastic-0.1.6.dist-info/METADATA
py_jelastic-0.1.6.dist-info/WHEEL
py_jelastic-0.1.6.dist-info/top_level.txt
py_jelastic-0.1.6.dist-info/RECORD
