Metadata-Version: 2.1
Name: py-jelastic
Version: 0.1.6
Summary: Jelastic API client library
Home-page: https://github.com/Onemind-Services-LLC/py-jelastic
Author: Abhimanyu Saharan
Author-email: asaharan@onemindservices.com
License: Apache2
Keywords: jelastic,api,client
Classifier: Intended Audience :: Developers
Classifier: Development Status :: 2 - Pre-Alpha
Classifier: Programming Language :: Python :: 3
Classifier: Programming Language :: Python :: 3.10
Classifier: Programming Language :: Python :: 3.11
License-File: LICENSE
Requires-Dist: requests
